{
  "episodeId": "seed_28_segment_17",
  "translationError": 6.125601059988555e-05,
  "rotationError": 0.00014017490851192527,
  "goal": {
    "position": {
      "x": 0.6640884678981421,
      "y": 0.21592733826009092
    },
    "rotation": {
      "theta": -0.6643973178912298
    }
  },
  "points": [
    {
      "timeFromStart": 0.0,
      "leftArm": {
        "joint0": 0.4693981640625,
        "joint1": 1.57079632679,
        "joint2": -1.57079632679,
        "joint3": 1.1977349999999998,
        "joint4": 0,
        "joint5": 1.9376452921248117,
        "joint6": 0
      },
      "rightArm": {
        "joint0": 0.44389999218750065,
        "joint1": 1.57079632679,
        "joint2": -1.57079632679,
        "joint3": -0.17835124999999996,
        "joint4": 0,
        "joint5": -0.7148757548918827,
        "joint6": 0
      },
      "cylinder": {
        "position": {
          "x": 0.7259169679910789,
          "y": 0.1539571816307454
        },
        "rotation": {
          "theta": 0.0
        }
      }
    },
    {
      "timeFromStart": 0.1,
      "leftArm": {
        "joint0": 0.5441467819693413,
        "joint1": 1.57079632679,
        "joint2": -1.57079632679,
        "joint3": 1.1102305820343263,
        "joint4": 0,
        "joint5": 1.9547046576341023,
        "joint6": 0
      },
      "rightArm": {
        "joint0": 0.5456113045684514,
        "joint1": 1.57079632679,
        "joint2": -1.57079632679,
        "joint3": -0.16288373735757916,
        "joint4": 0,
        "joint5": -0.7485079430265065,
        "joint6": 0
      },
      "cylinder": {
        "position": {
          "x": 0.7301146890150335,
          "y": 0.21377682329857248
        },
        "rotation": {
          "theta": -0.31427471561096
        }
      }
    },
    {
      "timeFromStart": 0.2,
      "leftArm": {
        "joint0": 0.5762763351877507,
        "joint1": 1.57079632679,
        "joint2": -1.57079632679,
        "joint3": 1.0324132046694054,
        "joint4": 0,
        "joint5": 1.9777887145586384,
        "joint6": 0
      },
      "rightArm": {
        "joint0": 0.5855607809603572,
        "joint1": 1.57079632679,
        "joint2": -1.57079632679,
        "joint3": -0.25325256549464514,
        "joint4": 0,
        "joint5": -0.7789851535747104,
        "joint6": 0
      },
      "cylinder": {
        "position": {
          "x": 0.7195697810707026,
          "y": 0.2596269075784403
        },
        "rotation": {
          "theta": -0.589817056860318
        }
      }
    },
    {
      "timeFromStart": 0.30000000000000004,
      "leftArm": {
        "joint0": 0.5730572556678964,
        "joint1": 1.57079632679,
        "joint2": -1.57079632679,
        "joint3": 1.0517067525354429,
        "joint4": 0,
        "joint5": 1.9736652085845832,
        "joint6": 0
      },
      "rightArm": {
        "joint0": 0.5042955683853846,
        "joint1": 1.57079632679,
        "joint2": -1.57079632679,
        "joint3": -0.423928381677492,
        "joint4": 0,
        "joint5": -0.8083929765258704,
        "joint6": 0
      },
      "cylinder": {
        "position": {
          "x": 0.7097779412748044,
          "y": 0.25374839236775315
        },
        "rotation": {
          "theta": -0.6158744818626288
        }
      }
    },
    {
      "timeFromStart": 0.4,
      "leftArm": {
        "joint0": 0.576202398219928,
        "joint1": 1.57079632679,
        "joint2": -1.57079632679,
        "joint3": 1.0829954867883307,
        "joint4": 0,
        "joint5": 1.964091399864833,
        "joint6": 0
      },
      "rightArm": {
        "joint0": 0.4328486395833726,
        "joint1": 1.57079632679,
        "joint2": -1.57079632679,
        "joint3": -0.5745364599806958,
        "joint4": 0,
        "joint5": -0.885097151275125,
        "joint6": 0
      },
      "cylinder": {
        "position": {
          "x": 0.6990504887233454,
          "y": 0.24463485616641148
        },
        "rotation": {
          "theta": -0.6264753987639167
        }
      }
    },
    {
      "timeFromStart": 0.5,
      "leftArm": {
        "joint0": 0.5781965503833493,
        "joint1": 1.57079632679,
        "joint2": -1.57079632679,
        "joint3": 1.119540701508114,
        "joint4": 0,
        "joint5": 1.953063510216982,
        "joint6": 0
      },
      "rightArm": {
        "joint0": 0.36599550557959837,
        "joint1": 1.57079632679,
        "joint2": -1.57079632679,
        "joint3": -0.7200752674919557,
        "joint4": 0,
        "joint5": -0.9824403024064965,
        "joint6": 0
      },
      "cylinder": {
        "position": {
          "x": 0.6860460167266988,
          "y": 0.23312059494792045
        },
        "rotation": {
          "theta": -0.6392124003025756
        }
      }
    },
    {
      "timeFromStart": 0.6,
      "leftArm": {
        "joint0": 0.5801981511414244,
        "joint1": 1.57079632679,
        "joint2": -1.57079632679,
        "joint3": 1.1600335868853413,
        "joint4": 0,
        "joint5": 1.9398443186074115,
        "joint6": 0
      },
      "rightArm": {
        "joint0": 0.30399161790161333,
        "joint1": 1.57079632679,
        "joint2": -1.57079632679,
        "joint3": -0.8601092542317277,
        "joint4": 0,
        "joint5": -1.0778944556507548,
        "joint6": 0
      },
      "cylinder": {
        "position": {
          "x": 0.6706421099769825,
          "y": 0.22068878676747816
        },
        "rotation": {
          "theta": -0.6564071282756078
        }
      }
    },
    {
      "timeFromStart": 0.7,
      "leftArm": {
        "joint0": 0.5804646905835599,
        "joint1": 1.57079632679,
        "joint2": -1.57079632679,
        "joint3": 1.1736315901554117,
        "joint4": 0,
        "joint5": 1.9353266111199812,
        "joint6": 0
      },
      "rightArm": {
        "joint0": 0.2880927332192889,
        "joint1": 1.57079632679,
        "joint2": -1.57079632679,
        "joint3": -0.8994462842319005,
        "joint4": 0,
        "joint5": -1.104557008773904,
        "joint6": 0
      },
      "cylinder": {
        "position": {
          "x": 0.6651035369725645,
          "y": 0.2166280514730154
        },
        "rotation": {
          "theta": -0.663246031593153
        }
      }
    },
    {
      "timeFromStart": 0.7999999999999999,
      "leftArm": {
        "joint0": 0.5805188598475763,
        "joint1": 1.57079632679,
        "joint2": -1.57079632679,
        "joint3": 1.1756078898797888,
        "joint4": 0,
        "joint5": 1.9344661747877663,
        "joint6": 0
      },
      "rightArm": {
        "joint0": 0.28699240735121784,
        "joint1": 1.57079632679,
        "joint2": -1.57079632679,
        "joint3": -0.9038829372243345,
        "joint4": 0,
        "joint5": -1.1117945064229446,
        "joint6": 0
      },
      "cylinder": {
        "position": {
          "x": 0.6642882551882068,
          "y": 0.2160541815807002
        },
        "rotation": {
          "theta": -0.6641381983798446
        }
      }
    },
    {
      "timeFromStart": 0.8999999999999999,
      "leftArm": {
        "joint0": 0.5805013744228832,
        "joint1": 1.57079632679,
        "joint2": -1.57079632679,
        "joint3": 1.1758375685039277,
        "joint4": 0,
        "joint5": 1.9341588397856717,
        "joint6": 0
      },
      "rightArm": {
        "joint0": 0.2879943491058987,
        "joint1": 1.57079632679,
        "joint2": -1.57079632679,
        "joint3": -0.9033803053204019,
        "joint4": 0,
        "joint5": -1.1161913157400278,
        "joint6": 0
      },
      "cylinder": {
        "position": {
          "x": 0.6641705159977462,
          "y": 0.2159695707739209
        },
        "rotation": {
          "theta": -0.6642578901668288
        }
      }
    },
    {
      "timeFromStart": 0.9999999999999999,
      "leftArm": {
        "joint0": 0.5804607670364762,
        "joint1": 1.57079632679,
        "joint2": -1.57079632679,
        "joint3": 1.1758343805233689,
        "joint4": 0,
        "joint5": 1.9339269643747954,
        "joint6": 0
      },
      "rightArm": {
        "joint0": 0.28922531604586965,
        "joint1": 1.57079632679,
        "joint2": -1.57079632679,
        "joint3": -0.9022470668379319,
        "joint4": 0,
        "joint5": -1.1199647863598823,
        "joint6": 0
      },
      "cylinder": {
        "position": {
          "x": 0.664147121699422,
          "y": 0.21594500264318323
        },
        "rotation": {
          "theta": -0.6642571429827179
        }
      }
    }
  ]
}