{
  "episodeId": "seed_44_segment_9",
  "translationError": 0.003571837994053821,
  "rotationError": 0.004094713312915665,
  "goal": {
    "position": {
      "x": 0.38121227893878273,
      "y": -0.01240829984623041
    },
    "rotation": {
      "theta": -0.376579222681541
    }
  },
  "points": [
    {
      "timeFromStart": 0.0,
      "leftArm": {
        "joint0": -1.1827674726562503,
        "joint1": 1.57079632679,
        "joint2": -1.57079632679,
        "joint3": -1.33681625,
        "joint4": 0,
        "joint5": -1.728964508324362,
        "joint6": 0
      },
      "rightArm": {
        "joint0": 0.3813135703125008,
        "joint1": 1.57079632679,
        "joint2": -1.57079632679,
        "joint3": 0.13090000000000002,
        "joint4": 0,
        "joint5": -0.8323969205932564,
        "joint6": 0
      },
      "cylinder": {
        "position": {
          "x": 0.3612827548369358,
          "y": -0.0967547700908908
        },
        "rotation": {
          "theta": 0.0
        }
      }
    },
    {
      "timeFromStart": 0.1,
      "leftArm": {
        "joint0": -1.038014341781869,
        "joint1": 1.57079632679,
        "joint2": -1.57079632679,
        "joint3": -1.2342185834077888,
        "joint4": 0,
        "joint5": -1.7298413291716854,
        "joint6": 0
      },
      "rightArm": {
        "joint0": 0.43516383109691126,
        "joint1": 1.57079632679,
        "joint2": -1.57079632679,
        "joint3": 0.13296570688985823,
        "joint4": 0,
        "joint5": -0.8323832059810929,
        "joint6": 0
      },
      "cylinder": {
        "position": {
          "x": 0.3839353187446907,
          "y": -0.07249871057901586
        },
        "rotation": {
          "theta": -0.2355242845936738
        }
      }
    },
    {
      "timeFromStart": 0.2,
      "leftArm": {
        "joint0": -0.9856579038635623,
        "joint1": 1.57079632679,
        "joint2": -1.57079632679,
        "joint3": -1.3533200043133828,
        "joint4": 0,
        "joint5": -1.7306450334311285,
        "joint6": 0
      },
      "rightArm": {
        "joint0": 0.5102402072910324,
        "joint1": 1.57079632679,
        "joint2": -1.57079632679,
        "joint3": 0.14005696369482756,
        "joint4": 0,
        "joint5": -0.8323512947482463,
        "joint6": 0
      },
      "cylinder": {
        "position": {
          "x": 0.38377806883919213,
          "y": -0.02947518584375884
        },
        "rotation": {
          "theta": -0.3728524864753592
        }
      }
    },
    {
      "timeFromStart": 0.30000000000000004,
      "leftArm": {
        "joint0": -0.9920843807805438,
        "joint1": 1.57079632679,
        "joint2": -1.57079632679,
        "joint3": -1.4127530356959284,
        "joint4": 0,
        "joint5": -1.7311150752126818,
        "joint6": 0
      },
      "rightArm": {
        "joint0": 0.5359010698375422,
        "joint1": 1.57079632679,
        "joint2": -1.57079632679,
        "joint3": 0.16409328815363727,
        "joint4": 0,
        "joint5": -0.8323320681627396,
        "joint6": 0
      },
      "cylinder": {
        "position": {
          "x": 0.379739457068983,
          "y": -0.019565467426945003
        },
        "rotation": {
          "theta": -0.3827124814642067
        }
      }
    },
    {
      "timeFromStart": 0.4,
      "leftArm": {
        "joint0": -0.9950310490686398,
        "joint1": 1.57079632679,
        "joint2": -1.57079632679,
        "joint3": -1.4399871561729667,
        "joint4": 0,
        "joint5": -1.7314488642912318,
        "joint6": 0
      },
      "rightArm": {
        "joint0": 0.5485119701929851,
        "joint1": 1.57079632679,
        "joint2": -1.57079632679,
        "joint3": 0.18545108281731204,
        "joint4": 0,
        "joint5": -0.832325367126123,
        "joint6": 0
      },
      "cylinder": {
        "position": {
          "x": 0.3780213791726958,
          "y": -0.016423859946199878
        },
        "rotation": {
          "theta": -0.3812801099737477
        }
      }
    },
    {
      "timeFromStart": 0.5,
      "leftArm": {
        "joint0": -0.9937437822962053,
        "joint1": 1.57079632679,
        "joint2": -1.57079632679,
        "joint3": -1.4382400779660014,
        "joint4": 0,
        "joint5": -1.7317410187745694,
        "joint6": 0
      },
      "rightArm": {
        "joint0": 0.5544776190765672,
        "joint1": 1.57079632679,
        "joint2": -1.57079632679,
        "joint3": 0.20387293805943807,
        "joint4": 0,
        "joint5": -0.8323094005105813,
        "joint6": 0
      },
      "cylinder": {
        "position": {
          "x": 0.3782008562719217,
          "y": -0.015938883774475297
        },
        "rotation": {
          "theta": -0.3811699745446274
        }
      }
    },
    {
      "timeFromStart": 0.6,
      "leftArm": {
        "joint0": -0.993113970472485,
        "joint1": 1.57079632679,
        "joint2": -1.57079632679,
        "joint3": -1.441110600002635,
        "joint4": 0,
        "joint5": -1.7320281703998213,
        "joint6": 0
      },
      "rightArm": {
        "joint0": 0.5592283325042068,
        "joint1": 1.57079632679,
        "joint2": -1.57079632679,
        "joint3": 0.21961476647584363,
        "joint4": 0,
        "joint5": -0.8322928209353437,
        "joint6": 0
      },
      "cylinder": {
        "position": {
          "x": 0.37849943658162905,
          "y": -0.015654783529631077
        },
        "rotation": {
          "theta": -0.3816422893261809
        }
      }
    },
    {
      "timeFromStart": 0.7,
      "leftArm": {
        "joint0": -0.9924341283673389,
        "joint1": 1.57079632679,
        "joint2": -1.57079632679,
        "joint3": -1.4371750456371437,
        "joint4": 0,
        "joint5": -1.7323192487148158,
        "joint6": 0
      },
      "rightArm": {
        "joint0": 0.5631539653296119,
        "joint1": 1.57079632679,
        "joint2": -1.57079632679,
        "joint3": 0.2332745099462722,
        "joint4": 0,
        "joint5": -0.8322767200210621,
        "joint6": 0
      },
      "cylinder": {
        "position": {
          "x": 0.37867321638785567,
          "y": -0.01561145310955523
        },
        "rotation": {
          "theta": -0.3809030055008736
        }
      }
    },
    {
      "timeFromStart": 0.7999999999999999,
      "leftArm": {
        "joint0": -0.9923172919277823,
        "joint1": 1.57079632679,
        "joint2": -1.57079632679,
        "joint3": -1.4404563716293866,
        "joint4": 0,
        "joint5": -1.7326095377153383,
        "joint6": 0
      },
      "rightArm": {
        "joint0": 0.5668036042804722,
        "joint1": 1.57079632679,
        "joint2": -1.57079632679,
        "joint3": 0.24521490924574307,
        "joint4": 0,
        "joint5": -0.8322595180090857,
        "joint6": 0
      },
      "cylinder": {
        "position": {
          "x": 0.3788257131810154,
          "y": -0.015412019027854112
        },
        "rotation": {
          "theta": -0.38105988771688354
        }
      }
    },
    {
      "timeFromStart": 0.8999999999999999,
      "leftArm": {
        "joint0": -0.9918075108035522,
        "joint1": 1.57079632679,
        "joint2": -1.57079632679,
        "joint3": -1.4369251277702442,
        "joint4": 0,
        "joint5": -1.7329032903813926,
        "joint6": 0
      },
      "rightArm": {
        "joint0": 0.5698377549512358,
        "joint1": 1.57079632679,
        "joint2": -1.57079632679,
        "joint3": 0.25586455859465235,
        "joint4": 0,
        "joint5": -0.8322426541076803,
        "joint6": 0
      },
      "cylinder": {
        "position": {
          "x": 0.37893823139875665,
          "y": -0.015407307364519045
        },
        "rotation": {
          "theta": -0.38046153601180144
        }
      }
    },
    {
      "timeFromStart": 0.9999999999999999,
      "leftArm": {
        "joint0": -0.9918081458782674,
        "joint1": 1.57079632679,
        "joint2": -1.57079632679,
        "joint3": -1.4402165902510724,
        "joint4": 0,
        "joint5": -1.7331977438517379,
        "joint6": 0
      },
      "rightArm": {
        "joint0": 0.5727729883656609,
        "joint1": 1.57079632679,
        "joint2": -1.57079632679,
        "joint3": 0.26541650625338353,
        "joint4": 0,
        "joint5": -0.8322247863127266,
        "joint6": 0
      },
      "cylinder": {
        "position": {
          "x": 0.3790421614646215,
          "y": -0.015245308271333599
        },
        "rotation": {
          "theta": -0.38067393599445665
        }
      }
    }
  ]
}